{"09800":["MX","09800","Estrella Culhuac\u00e1n","Ciudad de M\u00e9xico","DIF","Iztapalapa","007","Ciudad de M\u00e9xico","9","19.1694","-99.0257","3"],"09809":["MX","09809","Valle de Luces","Ciudad de M\u00e9xico","DIF","Iztapalapa","007","Ciudad de M\u00e9xico","9","22.7342","-102.6837","1"],"09810":["MX","09810","Minerva","Ciudad de M\u00e9xico","DIF","Iztapalapa","007","Ciudad de M\u00e9xico","9","22.8423","-102.6106","1"],"09819":["MX","09819","Valle del Sur","Ciudad de M\u00e9xico","DIF","Iztapalapa","007","Ciudad de M\u00e9xico","9","22.7729","-102.6307","1"],"09820":["MX","09820","La Mora Grande","Ciudad de M\u00e9xico","DIF","Iztapalapa","007","Ciudad de M\u00e9xico","9","24.5841","-101.3595","1"],"09828":["MX","09828","Ampliaci\u00f3n Ricardo Flores Mag\u00f3n","Ciudad de M\u00e9xico","DIF","Iztapalapa","007","Ciudad de M\u00e9xico","9","24.1729","-101.5009","1"],"09829":["MX","09829","Ampliaci\u00f3n El Santuario","Ciudad de M\u00e9xico","DIF","Iztapalapa","007","Ciudad de M\u00e9xico","9","24.5209","-100.8663","1"],"09830":["MX","09830","El Manto","Ciudad de M\u00e9xico","DIF","Iztapalapa","007","Ciudad de M\u00e9xico","9","24.285","-103.3769","1"],"09836":["MX","09836","Cuitlahuac","Ciudad de M\u00e9xico","DIF","Iztapalapa","007","Ciudad de M\u00e9xico","9","24.1907","-103.1557","1"],"09837":["MX","09837","San Miguel 8va. Ampliaci\u00f3n","Ciudad de M\u00e9xico","DIF","Iztapalapa","007","Ciudad de M\u00e9xico","9","24.0939","-103.0119","1"],"09838":["MX","09838","Plan de Iguala","Ciudad de M\u00e9xico","DIF","Iztapalapa","007","Ciudad de M\u00e9xico","9","24.2405","-102.7509","1"],"09839":["MX","09839","Ampliaci\u00f3n Paraje San Juan","Ciudad de M\u00e9xico","DIF","Iztapalapa","007","Ciudad de M\u00e9xico","9","24.0114","-102.4322","1"],"09840":["MX","09840","Los Reyes Culhuac\u00e1n","Ciudad de M\u00e9xico","DIF","Iztapalapa","007","Ciudad de M\u00e9xico","9","23.8212","-103.0835","1"],"09849":["MX","09849","Ampliaci\u00f3n Los Reyes","Ciudad de M\u00e9xico","DIF","Iztapalapa","007","Ciudad de M\u00e9xico","9","23.5549","-102.864","1"],"09850":["MX","09850","Predio Nautla","Ciudad de M\u00e9xico","DIF","Iztapalapa","007","Ciudad de M\u00e9xico","9","22.995","-102.6651","1"],"09856":["MX","09856","Estado de Veracruz","Ciudad de M\u00e9xico","DIF","Iztapalapa","007","Ciudad de M\u00e9xico","9","22.7861","-102.4566","1"],"09857":["MX","09857","San Francisco INFONAVIT","Ciudad de M\u00e9xico","DIF","Iztapalapa","007","Ciudad de M\u00e9xico","9","19.3055","-99.0763","3"],"09858":["MX","09858","Paraje San Juan Cerro","Ciudad de M\u00e9xico","DIF","Iztapalapa","007","Ciudad de M\u00e9xico","9","22.7861","-102.4566","1"],"09859":["MX","09859","Benito Ju\u00e1rez","Ciudad de M\u00e9xico","DIF","Iztapalapa","007","Ciudad de M\u00e9xico","9","19.3984","-99.1577","4"],"09860":["MX","09860","Espa\u00f1a","Ciudad de M\u00e9xico","DIF","Iztapalapa","007","Ciudad de M\u00e9xico","9","22.7539","-102.4988","1"],"09864":["MX","09864","Bertha Von Bloumer","Ciudad de M\u00e9xico","DIF","Iztapalapa","007","Ciudad de M\u00e9xico","9","22.7574","-102.3075","1"],"09868":["MX","09868","San Juan Estrella","Ciudad de M\u00e9xico","DIF","Iztapalapa","007","Ciudad de M\u00e9xico","9","22.4543","-102.3431","1"],"09869":["MX","09869","Plaza Estrella II","Ciudad de M\u00e9xico","DIF","Iztapalapa","007","Ciudad de M\u00e9xico","9","22.4465","-102.3548","1"],"09870":["MX","09870","12 de Diciembre","Ciudad de M\u00e9xico","DIF","Iztapalapa","007","Ciudad de M\u00e9xico","9","19.2902","-99.2579","3"],"09880":["MX","09880","Granjas Estrella","Ciudad de M\u00e9xico","DIF","Iztapalapa","007","Ciudad de M\u00e9xico","9","22.267","-101.9038","1"],"09889":["MX","09889","Rinconada Estrella","Ciudad de M\u00e9xico","DIF","Iztapalapa","007","Ciudad de M\u00e9xico","9","22.3152","-101.8132","1"],"09890":["MX","09890","Lomas Estrella","Ciudad de M\u00e9xico","DIF","Iztapalapa","007","Ciudad de M\u00e9xico","9","22.2792","-101.578","1"],"09897":["MX","09897","Carlos Jonguitud Barrios","Ciudad de M\u00e9xico","DIF","Iztapalapa","007","Ciudad de M\u00e9xico","9","22.0056","-101.5746","1"],"09899":["MX","09899","Lomas Estrella FOVISSSTE","Ciudad de M\u00e9xico","DIF","Iztapalapa","007","Ciudad de M\u00e9xico","9","22.2792","-101.578","1"]}