{"38160":["MX","38160","Primavera","Guanajuato","11","Apaseo el Grande","005","Apaseo el Grande","28","20.5097","-100.6239","3"],"38163":["MX","38163","Puente Colorado","Guanajuato","11","Apaseo el Grande","005","Apaseo el Grande","28","20.4311","-100.6665","3"],"38164":["MX","38164","Lindavista","Guanajuato","11","Apaseo el Grande","005","Apaseo el Grande","28","20.5755","-100.6217","1"],"38165":["MX","38165","15 de Mayo","Guanajuato","11","Apaseo el Grande","005","Apaseo el Grande","28","20.5755","-100.6217","3"],"38166":["MX","38166","Las Violetas","Guanajuato","11","Apaseo el Grande","005","Apaseo el Grande","28","20.5755","-100.6217","3"],"38167":["MX","38167","La Huerta","Guanajuato","11","Apaseo el Grande","005","Apaseo el Grande","28","20.5755","-100.6217","1"],"38168":["MX","38168","Las Higueras","Guanajuato","11","Apaseo el Grande","005","Apaseo el Grande","28","20.5755","-100.6217","1"],"38170":["MX","38170","Ixtla (San Miguel de Ixtla)","Guanajuato","11","Apaseo el Grande","005","","","20.6678","-100.5921","3"],"38173":["MX","38173","Rancho los Patoles","Guanajuato","11","Apaseo el Grande","005","","","20.6503","-100.6393","3"],"38174":["MX","38174","Garc\u00eda","Guanajuato","11","Apaseo el Grande","005","","","20.5815","-100.6938","4"],"38175":["MX","38175","Chavago","Guanajuato","11","Apaseo el Grande","005","","","20.6131","-100.6419","4"],"38176":["MX","38176","La Esperanza","Guanajuato","11","Apaseo el Grande","005","","","20.5614","-100.6308","4"],"38177":["MX","38177","Caleras de Ameche","Guanajuato","11","Apaseo el Grande","005","","","20.5613","-100.5601","4"],"38180":["MX","38180","Obrajuelo","Guanajuato","11","Apaseo el Grande","005","","","20.5937","-100.5592","4"],"38183":["MX","38183","Javier L\u00f3pez","Guanajuato","11","Apaseo el Grande","005","","","20.5921","-100.5262","3"],"38184":["MX","38184","Fandila","Guanajuato","11","Apaseo el Grande","005","","","20.5906","-100.4978","4"],"38185":["MX","38185","La Estancia","Guanajuato","11","Apaseo el Grande","005","","","20.5755","-100.6217","3"],"38186":["MX","38186","Fuentes de Balvanera","Guanajuato","11","Apaseo el Grande","005","","","20.5575","-100.5389","3"],"38187":["MX","38187","Ameche","Guanajuato","11","Apaseo el Grande","005","","","20.5526","-100.5837","4"],"38188":["MX","38188","La Loma Alta","Guanajuato","11","Apaseo el Grande","005","","","20.5247","-100.5853","3"],"38190":["MX","38190","San Pedro Tenango","Guanajuato","11","Apaseo el Grande","005","","","20.5077","-100.6325","4"],"38194":["MX","38194","San Jos\u00e9 Agua Azul","Guanajuato","11","Apaseo el Grande","005","","","20.4866","-100.6559","4"],"38195":["MX","38195","Puente del \u00c1guila","Guanajuato","11","Apaseo el Grande","005","","","20.4972","-100.6419","4"],"38196":["MX","38196","Felipe Herrera Contreras","Guanajuato","11","Apaseo el Grande","005","","","20.5325","-100.7128","4"],"38197":["MX","38197","Susana","Guanajuato","11","Apaseo el Grande","005","","","20.5281","-100.7269","4"],"38198":["MX","38198","Bordo Blanco (Rancho el Sagrado)","Guanajuato","11","Apaseo el Grande","005","","","20.5544","-100.7208","4"],"38100":["MX","38100","San Antonio de Gallardo","Guanajuato","11","Celaya","007","","","20.6283","-100.7678","4"],"38104":["MX","38104","Presa Blanca","Guanajuato","11","Celaya","007","","","20.6415","-100.7924","4"],"38105":["MX","38105","Los Tres Puentes","Guanajuato","11","Celaya","007","","","20.6639","-100.7792","4"],"38106":["MX","38106","San Antonio Espinosa","Guanajuato","11","Celaya","007","","","20.6368","-100.8494","3"],"38107":["MX","38107","San Jos\u00e9 de Mendoza","Guanajuato","11","Celaya","007","","","20.5375","-100.7878","1"],"38110":["MX","38110","San Jos\u00e9 de Guanajuato","Guanajuato","11","Celaya","007","","","20.556","-100.8928","4"],"38114":["MX","38114","Puerta del Monte (Elguera)","Guanajuato","11","Celaya","007","","","20.5622","-100.8858","4"],"38115":["MX","38115","Parque Tabachines","Guanajuato","11","Celaya","007","","","20.535","-100.8612","3"],"38116":["MX","38116","Santa Mar\u00eda","Guanajuato","11","Celaya","007","","","20.4403","-100.8003","4"],"38117":["MX","38117","El Puente","Guanajuato","11","Celaya","007","","","20.5236","-100.8967","4"],"38118":["MX","38118","El \u00c1lamo","Guanajuato","11","Celaya","007","","","20.5522","-100.8961","4"],"38119":["MX","38119","Celaya [Aeropuerto]","Guanajuato","11","Celaya","007","","","20.538","-100.8607","1"],"38120":["MX","38120","Tener\u00eda del Santuario","Guanajuato","11","Celaya","007","","","20.5996","-100.7979","4"],"38123":["MX","38123","San Cayetano","Guanajuato","11","Celaya","007","","","20.6036","-100.8202","4"],"38126":["MX","38126","Ejido de Silva (San Isidro)","Guanajuato","11","Celaya","007","","","20.5783","-100.8522","3"],"38127":["MX","38127","San Luis Rey","Guanajuato","11","Celaya","007","","","20.5706","-100.7865","4"],"38130":["MX","38130","San Miguel Octopan","Guanajuato","11","Celaya","007","","","20.5743","-100.7478","4"],"38133":["MX","38133","Los Galvanes","Guanajuato","11","Celaya","007","","","20.6494","-100.7101","4"],"38135":["MX","38135","J\u00e1uregui","Guanajuato","11","Celaya","007","","","20.5928","-100.7194","4"],"38136":["MX","38136","San Lorenzo","Guanajuato","11","Celaya","007","","","20.4669","-100.7197","4"],"38137":["MX","38137","San Jos\u00e9 de la Presa","Guanajuato","11","Celaya","007","","","20.6111","-100.7522","4"],"38140":["MX","38140","San Francisco","Guanajuato","11","Celaya","007","","","20.4081","-100.7564","4"],"38143":["MX","38143","San Isidro de Trojes","Guanajuato","11","Celaya","007","","","20.5138","-100.7673","4"],"38144":["MX","38144","Santa Anita","Guanajuato","11","Celaya","007","","","20.4703","-100.815","4"],"38145":["MX","38145","San Lorenzo","Guanajuato","11","Celaya","007","","","20.4669","-100.7197","4"],"38146":["MX","38146","Juan Mart\u00edn","Guanajuato","11","Celaya","007","","","20.473","-100.7469","4"],"38147":["MX","38147","San Jos\u00e9 el Nuevo","Guanajuato","11","Celaya","007","","","20.4439","-100.7719","4"],"38150":["MX","38150","Rinc\u00f3n de Tamayo Centro","Guanajuato","11","Celaya","007","Rinc\u00f3n de Tamayo","25","20.4237","-100.7741","1"],"38152":["MX","38152","La Cruz","Guanajuato","11","Celaya","007","Rinc\u00f3n de Tamayo","25","20.4569","-100.7958","4"],"38153":["MX","38153","San Juan","Guanajuato","11","Celaya","007","Rinc\u00f3n de Tamayo","25","20.4237","-100.7741","1"],"38154":["MX","38154","San Marcos","Guanajuato","11","Celaya","007","Rinc\u00f3n de Tamayo","25","20.5375","-100.7878","1"],"38155":["MX","38155","La Resurrecci\u00f3n","Guanajuato","11","Celaya","007","Rinc\u00f3n de Tamayo","25","20.4248","-100.7608","4"],"38156":["MX","38156","Canoas (Congregaci\u00f3n de Canoas)","Guanajuato","11","Celaya","007","","","20.4156","-100.7129","4"],"38157":["MX","38157","Santa Rosa de Lima","Guanajuato","11","Celaya","007","","","20.3917","-100.7268","4"],"38158":["MX","38158","Ojo Seco","Guanajuato","11","Celaya","007","","","20.3869","-100.7966","4"],"38159":["MX","38159","El Sauz (El Sauz de Villase\u00f1or)","Guanajuato","11","Celaya","007","","","20.4106","-100.7967","4"]}