{"40480":["MX","40480","Acapetlahuaya","Guerrero","12","General Canuto A. Neri","031","","","18.4194","-100.0724","4"],"40481":["MX","40481","San Sim\u00f3n Ostumba","Guerrero","12","General Canuto A. Neri","031","","","18.4205","-100.0725","1"],"40482":["MX","40482","L\u00eddice","Guerrero","12","General Canuto A. Neri","031","","","18.4671","-100.0196","4"],"40483":["MX","40483","El Teteyo","Guerrero","12","General Canuto A. Neri","031","","","18.4205","-100.0725","1"],"40485":["MX","40485","El Salto","Guerrero","12","General Canuto A. Neri","031","","","18.4372","-100.036","4"],"40486":["MX","40486","Ocotepec","Guerrero","12","General Canuto A. Neri","031","","","18.4216","-100.1109","4"],"40487":["MX","40487","El Cant\u00f3n","Guerrero","12","General Canuto A. Neri","031","","","18.4066","-100.047","4"],"40488":["MX","40488","Las Ceibitas","Guerrero","12","General Canuto A. Neri","031","","","18.4008","-100.0829","4"],"40489":["MX","40489","La Esmeralda","Guerrero","12","General Canuto A. Neri","031","","","18.3458","-100.082","4"],"40490":["MX","40490","Hueycal\u00ed el Viejo","Guerrero","12","General Canuto A. Neri","031","","","18.4357","-100.1328","3"],"40491":["MX","40491","Filo Hueycal\u00ed","Guerrero","12","General Canuto A. Neri","031","","","18.468","-100.1343","3"],"40493":["MX","40493","Sabino Alto","Guerrero","12","General Canuto A. Neri","031","","","18.4024","-100.1189","4"],"40494":["MX","40494","Mina de La Concepci\u00f3n","Guerrero","12","General Canuto A. Neri","031","","","18.4331","-100.1907","4"],"40496":["MX","40496","El Barranc\u00f3n","Guerrero","12","General Canuto A. Neri","031","","","18.4313","-100.1289","4"],"40497":["MX","40497","La Providencia","Guerrero","12","General Canuto A. Neri","031","","","18.4048","-100.1453","4"],"40498":["MX","40498","Amates Grandes","Guerrero","12","General Canuto A. Neri","031","","","18.3942","-100.1168","4"],"40430":["MX","40430","Ixcateopan de Cuauht\u00e9moc","Guerrero","12","Ixcateopan de Cuauht\u00e9moc","037","","","18.5014","-99.7914","4"],"40431":["MX","40431","San Pedro Guadalupe","Guerrero","12","Ixcateopan de Cuauht\u00e9moc","037","","","18.548","-99.7625","4"],"40436":["MX","40436","Romita","Guerrero","12","Ixcateopan de Cuauht\u00e9moc","037","","","18.4879","-99.8112","4"],"40440":["MX","40440","Simatel","Guerrero","12","Ixcateopan de Cuauht\u00e9moc","037","","","18.4636","-99.8279","4"],"40441":["MX","40441","Pachivia","Guerrero","12","Ixcateopan de Cuauht\u00e9moc","037","","","18.4628","-99.8212","1"],"40444":["MX","40444","Pipincatla","Guerrero","12","Ixcateopan de Cuauht\u00e9moc","037","","","18.4494","-99.8069","4"],"40450":["MX","40450","El Potrero","Guerrero","12","Ixcateopan de Cuauht\u00e9moc","037","","","18.4536","-99.7453","4"],"40451":["MX","40451","Xalostoc","Guerrero","12","Ixcateopan de Cuauht\u00e9moc","037","","","18.4259","-99.7309","4"],"40453":["MX","40453","Teucizapan","Guerrero","12","Ixcateopan de Cuauht\u00e9moc","037","","","18.4568","-99.7142","4"],"40460":["MX","40460","Ixcapuzalco","Guerrero","12","Pedro Ascencio Alquisiras","047","","","18.512","-99.8875","4"],"40461":["MX","40461","Otates","Guerrero","12","Pedro Ascencio Alquisiras","047","","","18.6046","-99.8863","4"],"40463":["MX","40463","Acatla","Guerrero","12","Pedro Ascencio Alquisiras","047","","","18.5535","-99.9099","4"],"40464":["MX","40464","Tepatulco","Guerrero","12","Pedro Ascencio Alquisiras","047","","","18.5368","-99.9097","4"],"40465":["MX","40465","Cuajinicuila","Guerrero","12","Pedro Ascencio Alquisiras","047","","","18.523","-99.9345","4"],"40466":["MX","40466","Ixcapaneca","Guerrero","12","Pedro Ascencio Alquisiras","047","","","18.5447","-99.8692","4"],"40469":["MX","40469","Rinc\u00f3n de Jumapa","Guerrero","12","Pedro Ascencio Alquisiras","047","","","18.4375","-99.9519","4"],"40470":["MX","40470","San Pablo","Guerrero","12","Pedro Ascencio Alquisiras","047","","","18.6081","-99.7796","4"],"40471":["MX","40471","Tejocotes","Guerrero","12","Pedro Ascencio Alquisiras","047","","","18.6111","-99.7952","4"],"40472":["MX","40472","Azulaquez","Guerrero","12","Pedro Ascencio Alquisiras","047","","","18.5793","-99.8081","4"],"40473":["MX","40473","Los Sauces","Guerrero","12","Pedro Ascencio Alquisiras","047","","","18.5537","-99.7809","4"],"40474":["MX","40474","Metlixtapa","Guerrero","12","Pedro Ascencio Alquisiras","047","","","18.5476","-99.8473","4"],"40476":["MX","40476","Cerro Grande","Guerrero","12","Pedro Ascencio Alquisiras","047","","","18.4982","-99.8358","4"],"40477":["MX","40477","Chicahuaca","Guerrero","12","Pedro Ascencio Alquisiras","047","","","18.5243","-99.826","4"],"40479":["MX","40479","Rancho Viejo","Guerrero","12","Pedro Ascencio Alquisiras","047","","","18.4779","-99.8667","4"],"40400":["MX","40400","El Sabino","Guerrero","12","Teloloapan","058","Teloloapan","24","18.4442","-100.0098","4"],"40402":["MX","40402","Los Aguajes","Guerrero","12","Teloloapan","058","","","18.4125","-99.9583","4"],"40403":["MX","40403","Villa de Ayala","Guerrero","12","Teloloapan","058","","","18.3972","-100.03","4"],"40404":["MX","40404","R\u00edo de Sayulapa","Guerrero","12","Teloloapan","058","","","18.355","-99.9151","3"],"40405":["MX","40405","Cruz Blanca","Guerrero","12","Teloloapan","058","","","18.3306","-100.0832","4"],"40406":["MX","40406","La Magdalena","Guerrero","12","Teloloapan","058","","","18.4323","-99.8615","4"],"40407":["MX","40407","Dolores","Guerrero","12","Teloloapan","058","","","18.5172","-100.0011","4"],"40408":["MX","40408","El Duraznal","Guerrero","12","Teloloapan","058","","","18.3183","-100.0216","4"],"40409":["MX","40409","Ranchos Nuevos","Guerrero","12","Teloloapan","058","","","18.4159","-100.0047","4"],"40410":["MX","40410","Chapa","Guerrero","12","Teloloapan","058","","","18.3256","-99.8246","4"],"40411":["MX","40411","Miacatzingo","Guerrero","12","Teloloapan","058","","","18.3626","-99.7008","4"],"40412":["MX","40412","Tonalapa del R\u00edo","Guerrero","12","Teloloapan","058","","","18.342","-99.6916","4"],"40413":["MX","40413","Los Sabinos","Guerrero","12","Teloloapan","058","","","18.3649","-99.7586","4"],"40414":["MX","40414","Tlacuitlapa","Guerrero","12","Teloloapan","058","","","18.3286","-99.7073","4"],"40415":["MX","40415","Coatepec de los Costales","Guerrero","12","Teloloapan","058","","","18.2445","-99.9075","3"],"40416":["MX","40416","Tonalapa del R\u00edo Cuauht\u00e9moc","Guerrero","12","Teloloapan","058","","","18.3558","-99.6547","3"],"40417":["MX","40417","Hacienda de Oculixtlahuacan","Guerrero","12","Teloloapan","058","","","18.4046","-99.6855","4"],"40420":["MX","40420","El Tanque","Guerrero","12","Teloloapan","058","","","18.3419","-99.8767","4"],"40421":["MX","40421","Huerta Grande Sur","Guerrero","12","Teloloapan","058","","","18.2849","-99.8826","4"],"40422":["MX","40422","Apatzingan","Guerrero","12","Teloloapan","058","","","18.2643","-99.8207","4"],"40423":["MX","40423","Oxtotitl\u00e1n","Guerrero","12","Teloloapan","058","","","18.19","-99.9325","4"],"40424":["MX","40424","Palo Verde","Guerrero","12","Teloloapan","058","","","18.3583","-99.9141","3"],"40425":["MX","40425","Pezuapilla y Naranjo","Guerrero","12","Teloloapan","058","","","18.2503","-99.8869","4"],"40426":["MX","40426","Laguna Seca","Guerrero","12","Teloloapan","058","","","18.2712","-99.9732","4"],"40428":["MX","40428","Tehuixtla","Guerrero","12","Teloloapan","058","","","18.3168","-99.933","4"],"40429":["MX","40429","El Plan del Sabino","Guerrero","12","Teloloapan","058","","","18.4442","-100.0098","4"]}