{"42280":["MX","42280","Chapulhuac\u00e1n","Hidalgo","13","Chapulhuac\u00e1n","018","","","21.1573","-98.9036","4"],"42282":["MX","42282","El Pescado","Hidalgo","13","Chapulhuac\u00e1n","018","","","21.1291","-98.889","4"],"42283":["MX","42283","Nueva Esperanza","Hidalgo","13","Chapulhuac\u00e1n","018","","","21.1284","-98.9496","3"],"42284":["MX","42284","La Joya del Zopilote","Hidalgo","13","Chapulhuac\u00e1n","018","","","21.1501","-98.9368","4"],"42285":["MX","42285","La Casa Verde","Hidalgo","13","Chapulhuac\u00e1n","018","","","21.1744","-98.9802","4"],"42286":["MX","42286","El Sabino","Hidalgo","13","Chapulhuac\u00e1n","018","","","21.1633","-98.8847","4"],"42290":["MX","42290","Palo Semita","Hidalgo","13","Chapulhuac\u00e1n","018","","","21.105","-99.0019","4"],"42291":["MX","42291","Iglesia Vieja (Iglesia Nueva)","Hidalgo","13","Chapulhuac\u00e1n","018","","","21.1068","-98.9672","4"],"42294":["MX","42294","Palomas","Hidalgo","13","Chapulhuac\u00e1n","018","","","21.0752","-99.0289","4"],"42295":["MX","42295","El Coyol","Hidalgo","13","Chapulhuac\u00e1n","018","","","21.0627","-98.9995","4"],"42296":["MX","42296","El Hualul","Hidalgo","13","Chapulhuac\u00e1n","018","","","21.1014","-99.0211","4"],"42298":["MX","42298","Santa Mar\u00eda de \u00c1lamos","Hidalgo","13","Chapulhuac\u00e1n","018","","","21.1356","-98.9703","4"],"42200":["MX","42200","Jacala Centro","Hidalgo","13","Jacala de Ledezma","031","","","20.9554","-99.2544","3"],"42201":["MX","42201","Toribio","Hidalgo","13","Jacala de Ledezma","031","","","21.0148","-99.1771","4"],"42203":["MX","42203","El S\u00f3tano","Hidalgo","13","Jacala de Ledezma","031","","","21.0069","-99.1359","4"],"42204":["MX","42204","Puerto del Mezquite (La Calera)","Hidalgo","13","Jacala de Ledezma","031","","","20.9453","-99.0833","3"],"42205":["MX","42205","Co\u00f1ecito","Hidalgo","13","Jacala de Ledezma","031","","","21.0437","-99.1243","4"],"42208":["MX","42208","Los Frijoles (Jacarandas)","Hidalgo","13","Jacala de Ledezma","031","","","21.009","-99.2007","4"],"42209":["MX","42209","Los Hoyos","Hidalgo","13","Jacala de Ledezma","031","","","20.9868","-99.2215","4"],"42210":["MX","42210","Vado Hondo","Hidalgo","13","Jacala de Ledezma","031","","","20.8456","-99.0318","4"],"42211":["MX","42211","El Pi\u00f1\u00f3n","Hidalgo","13","Jacala de Ledezma","031","","","20.9488","-99.2136","4"],"42215":["MX","42215","El Carrizal","Hidalgo","13","Jacala de Ledezma","031","","","20.8847","-99.1247","4"],"42260":["MX","42260","La Misi\u00f3n","Hidalgo","13","La Misi\u00f3n","040","","","21.0988","-99.1237","4"],"42262":["MX","42262","Loma de Naranjos","Hidalgo","13","La Misi\u00f3n","040","","","21.1153","-99.0877","4"],"42263":["MX","42263","Mesa de Pilas","Hidalgo","13","La Misi\u00f3n","040","","","21.1111","-99.1386","4"],"42264":["MX","42264","Piedra Larga","Hidalgo","13","La Misi\u00f3n","040","","","21.0433","-99.0817","4"],"42265":["MX","42265","El Fresno","Hidalgo","13","La Misi\u00f3n","040","","","21.0886","-99.0488","4"],"42266":["MX","42266","La Joya","Hidalgo","13","La Misi\u00f3n","040","","","21.1025","-99.0645","4"],"42267":["MX","42267","Loma de Macangui","Hidalgo","13","La Misi\u00f3n","040","","","21.0668","-99.1122","3"],"42268":["MX","42268","El Mexe Grande","Hidalgo","13","La Misi\u00f3n","040","","","21.0466","-99.0375","4"],"42273":["MX","42273","La Hondura","Hidalgo","13","La Misi\u00f3n","040","","","21.0136","-99.0775","4"],"42274":["MX","42274","Nuevo Linares","Hidalgo","13","La Misi\u00f3n","040","","","21.0402","-98.9976","4"],"42275":["MX","42275","Damathi","Hidalgo","13","La Misi\u00f3n","040","","","21.0027","-99.0807","4"],"42240":["MX","42240","Pacula","Hidalgo","13","Pacula","047","","","21.0507","-99.2958","4"],"42241":["MX","42241","Vicente Guerrero (Presidio)","Hidalgo","13","Pacula","047","","","21.0558","-99.2812","1"],"42245":["MX","42245","El Huizachal","Hidalgo","13","Pacula","047","","","21.029","-99.2279","4"],"42246":["MX","42246","Lagunillas","Hidalgo","13","Pacula","047","","","21.0877","-99.32","4"],"42250":["MX","42250","Jiliapan","Hidalgo","13","Pacula","047","","","20.9811","-99.3436","4"],"42251":["MX","42251","San Francisco","Hidalgo","13","Pacula","047","","","20.9783","-99.3581","4"],"42253":["MX","42253","Puerto Grande","Hidalgo","13","Pacula","047","","","20.9057","-99.3277","4"],"42254":["MX","42254","La Calera","Hidalgo","13","Pacula","047","","","20.9983","-99.3164","4"],"42255":["MX","42255","Sajunta de las Minas","Hidalgo","13","Pacula","047","","","20.9235","-99.2815","3"],"42256":["MX","42256","Rancho Nuevo","Hidalgo","13","Pacula","047","","","20.9564","-99.2921","4"],"42257":["MX","42257","El Baile","Hidalgo","13","Pacula","047","","","20.9266","-99.3822","4"],"42259":["MX","42259","El Mezquite","Hidalgo","13","Pacula","047","","","20.8941","-99.2879","4"],"42220":["MX","42220","Colosio","Hidalgo","13","Pisaflores","049","","","21.1612","-98.9999","3"],"42221":["MX","42221","La Pechuga","Hidalgo","13","Pisaflores","049","","","21.1831","-99.04","4"],"42222":["MX","42222","El Magueyal","Hidalgo","13","Pisaflores","049","","","21.17","-99.0161","4"],"42223":["MX","42223","Cuicillos","Hidalgo","13","Pisaflores","049","","","21.2396","-99.0062","3"],"42224":["MX","42224","Tlacuilola","Hidalgo","13","Pisaflores","049","","","21.2326","-99.059","4"],"42225":["MX","42225","La Presa","Hidalgo","13","Pisaflores","049","","","21.2015","-98.9597","4"],"42230":["MX","42230","Cerro de Guadalupe","Hidalgo","13","Pisaflores","049","","","21.2139","-98.9392","4"],"42232":["MX","42232","Tripuente","Hidalgo","13","Pisaflores","049","","","21.2489","-98.9536","4"],"42233":["MX","42233","Puerto Obscuro","Hidalgo","13","Pisaflores","049","","","21.2899","-98.9744","4"],"42234":["MX","42234","Gargantilla","Hidalgo","13","Pisaflores","049","","","21.2653","-98.9578","4"],"42235":["MX","42235","Chalahuitito","Hidalgo","13","Pisaflores","049","","","21.2671","-98.9312","4"],"42236":["MX","42236","El Aguacate","Hidalgo","13","Pisaflores","049","","","21.2346","-98.9888","3"],"42237":["MX","42237","El Platanito","Hidalgo","13","Pisaflores","049","","","21.2453","-98.989","4"],"42239":["MX","42239","Rancho Nuevo","Hidalgo","13","Pisaflores","049","","","21.2041","-98.915","4"]}