{"43460":["MX","43460","Agua Blanca de Iturbide Centro","Hidalgo","HID","Agua Blanca de Iturbide","004","","","20.3603","-98.3854","1"],"43463":["MX","43463","El Capul\u00edn","Hidalgo","HID","Agua Blanca de Iturbide","004","","","20.3603","-98.3854","1"],"43464":["MX","43464","El Tr\u00e9bol","Hidalgo","HID","Agua Blanca de Iturbide","004","","","20.3603","-98.3854","1"],"43468":["MX","43468","Palizar","Hidalgo","HID","Agua Blanca de Iturbide","004","","","20.3744","-98.3886","4"],"43469":["MX","43469","Plan Grande","Hidalgo","HID","Agua Blanca de Iturbide","004","","","20.3887","-98.3725","4"],"43470":["MX","43470","San Pedrito (Potrerillos)","Hidalgo","HID","Agua Blanca de Iturbide","004","","","20.39","-98.3435","3"],"43472":["MX","43472","El X\u00fachitl","Hidalgo","HID","Agua Blanca de Iturbide","004","","","20.4125","-98.312","4"],"43473":["MX","43473","La Torre","Hidalgo","HID","Agua Blanca de Iturbide","004","","","20.3447","-98.342","4"],"43474":["MX","43474","Milpa Vieja (Apulco)","Hidalgo","HID","Agua Blanca de Iturbide","004","","","20.3114","-98.3407","4"],"43420":["MX","43420","Huehuetla Centro","Hidalgo","HID","Huehuetla","027","","","20.4415","-98.0925","1"],"43421":["MX","43421","R\u00edo Blanco","Hidalgo","HID","Huehuetla","027","","","20.4111","-98.0851","4"],"43422":["MX","43422","Santa In\u00e9s","Hidalgo","HID","Huehuetla","027","","","20.4548","-98.09","4"],"43423":["MX","43423","Arroyo Negro","Hidalgo","HID","Huehuetla","027","","","20.4415","-98.0925","1"],"43424":["MX","43424","El Chamizal","Hidalgo","HID","Huehuetla","027","","","20.4842","-98.0776","4"],"43425":["MX","43425","Acuautla","Hidalgo","HID","Huehuetla","027","","","20.49","-98.0339","4"],"43426":["MX","43426","Santa \u00darsula","Hidalgo","HID","Huehuetla","027","","","20.4203","-98.1048","4"],"43427":["MX","43427","Cantarranas","Hidalgo","HID","Huehuetla","027","","","20.4408","-98.0703","4"],"43430":["MX","43430","San Lorenzo Achiotepec","Hidalgo","HID","Huehuetla","027","","","20.5973","-98.0688","4"],"43431":["MX","43431","San Esteban","Hidalgo","HID","Huehuetla","027","","","20.5445","-98.06","4"],"43433":["MX","43433","El Salto del Agua","Hidalgo","HID","Huehuetla","027","","","20.5897","-98.0375","4"],"43434":["MX","43434","El Encinal","Hidalgo","HID","Huehuetla","027","","","20.5858","-98.0491","4"],"43435":["MX","43435","La Joya","Hidalgo","HID","Huehuetla","027","","","20.6183","-98.0917","4"],"43436":["MX","43436","San Antonio","Hidalgo","HID","Huehuetla","027","","","20.4568","-98.0348","4"],"43400":["MX","43400","Metepec Centro","Hidalgo","HID","Metepec","035","","","20.2484","-98.3391","1"],"43401":["MX","43401","Tortugas","Hidalgo","HID","Metepec","035","","","20.2403","-98.3531","4"],"43403":["MX","43403","El Acocul","Hidalgo","HID","Metepec","035","","","20.2192","-98.3741","4"],"43404":["MX","43404","Palo Gordo (Ejido Nopalillo)","Hidalgo","HID","Metepec","035","","","20.2233","-98.3068","3"],"43406":["MX","43406","Buena Vista","Hidalgo","HID","Metepec","035","","","20.2607","-98.2972","3"],"43407":["MX","43407","El Vesubio","Hidalgo","HID","Metepec","035","","","20.2661","-98.405","4"],"43408":["MX","43408","Ignacio Zaragoza","Hidalgo","HID","Metepec","035","","","20.2668","-98.3479","4"],"43409":["MX","43409","Temaxcalillos","Hidalgo","HID","Metepec","035","","","20.2664","-98.3609","4"],"43410":["MX","43410","El Casco","Hidalgo","HID","Metepec","035","","","20.3158","-98.3353","4"],"43411":["MX","43411","Ferrer\u00eda de Apulco","Hidalgo","HID","Metepec","035","","","20.3028","-98.3438","4"],"43412":["MX","43412","San Diego","Hidalgo","HID","Metepec","035","","","20.2917","-98.3734","4"],"43440":["MX","43440","Los Reyes","Hidalgo","HID","San Bartolo Tutotepec","053","","","20.4045","-98.1871","3"],"43442":["MX","43442","Las Juntas","Hidalgo","HID","San Bartolo Tutotepec","053","","","20.3897","-98.2116","3"],"43443":["MX","43443","Los Manantiales","Hidalgo","HID","San Bartolo Tutotepec","053","","","20.4052","-98.211","4"],"43444":["MX","43444","El Rinc\u00f3n","Hidalgo","HID","San Bartolo Tutotepec","053","","","20.4055","-98.2329","4"],"43445":["MX","43445","El Para\u00edso Tierra Fuerte","Hidalgo","HID","San Bartolo Tutotepec","053","","","20.4454","-98.1323","4"],"43446":["MX","43446","Cerro Negro","Hidalgo","HID","San Bartolo Tutotepec","053","","","20.5","-98.2","4"],"43447":["MX","43447","Xuchitl\u00e1n","Hidalgo","HID","San Bartolo Tutotepec","053","","","20.4535","-98.2504","4"],"43448":["MX","43448","El Tigrillo","Hidalgo","HID","San Bartolo Tutotepec","053","","","20.3646","-98.2923","4"],"43449":["MX","43449","Agua Escondida","Hidalgo","HID","San Bartolo Tutotepec","053","","","20.4635","-98.2344","4"],"43450":["MX","43450","El Hongo","Hidalgo","HID","San Bartolo Tutotepec","053","","","20.5919","-98.1051","4"],"43451":["MX","43451","Palo Gordo","Hidalgo","HID","San Bartolo Tutotepec","053","","","20.49","-98.2086","4"],"43452":["MX","43452","El Templado","Hidalgo","HID","San Bartolo Tutotepec","053","","","20.4798","-98.1043","4"],"43453":["MX","43453","El Cojolite","Hidalgo","HID","San Bartolo Tutotepec","053","","","20.5032","-98.1393","4"],"43454":["MX","43454","El Nenjo","Hidalgo","HID","San Bartolo Tutotepec","053","","","20.5092","-98.2228","4"],"43455":["MX","43455","El Nanjo","Hidalgo","HID","San Bartolo Tutotepec","053","","","20.5235","-98.0785","4"],"43456":["MX","43456","El Popotillo Grande","Hidalgo","HID","San Bartolo Tutotepec","053","","","20.4578","-98.1872","4"],"43459":["MX","43459","Cerro Pel\u00f3n","Hidalgo","HID","San Bartolo Tutotepec","053","","","20.3847","-98.2925","4"],"43480":["MX","43480","Villa Tenango de Doria Centro","Hidalgo","HID","Tenango de Doria","060","","","20.3316","-98.2441","1"],"43483":["MX","43483","El Damo","Hidalgo","HID","Tenango de Doria","060","","","20.3278","-98.2208","4"],"43484":["MX","43484","La Loma","Hidalgo","HID","Tenango de Doria","060","","","20.3422","-98.2275","4"],"43485":["MX","43485","El Porvenir","Hidalgo","HID","Tenango de Doria","060","","","20.3316","-98.2441","1"],"43486":["MX","43486","La Cruz de Tenango","Hidalgo","HID","Tenango de Doria","060","","","20.2827","-98.2737","4"],"43487":["MX","43487","El Zetoy","Hidalgo","HID","Tenango de Doria","060","","","20.3364","-98.2469","4"],"43488":["MX","43488","La Reforma","Hidalgo","HID","Tenango de Doria","060","","","20.3762","-98.2542","4"],"43490":["MX","43490","San Francisco la Laguna","Hidalgo","HID","Tenango de Doria","060","","","20.3659","-98.1284","4"],"43491":["MX","43491","El Aguacate","Hidalgo","HID","Tenango de Doria","060","","","20.3719","-98.1878","4"],"43493":["MX","43493","San Isidro la Laguna","Hidalgo","HID","Tenango de Doria","060","","","20.3789","-98.1286","4"],"43494":["MX","43494","El Xaj\u00e1","Hidalgo","HID","Tenango de Doria","060","","","20.3781","-98.1878","4"],"43495":["MX","43495","L\u00f3pez Mateos (La Colonia)","Hidalgo","HID","Tenango de Doria","060","","","20.3553","-98.1719","4"],"43496":["MX","43496","El Deque\u00f1a","Hidalgo","HID","Tenango de Doria","060","","","20.3529","-98.23","4"]}